Workbook

Sheet order_items
A1: order_id | B1: item_id | C1: product_id | D1: quantity | E1: list_price | F1: discount | G1: Total Price | H1: Product_Name | I1: Total sales
A2: 1 | B2: 1 | C2: 20 | D2: 1 | E2: 599.99 | F2: 0.2 | G2: =(E2*D2)-F2 -> 599.79 | H2: =_xlfn.XLOOKUP(C2,Product!A:A,Product!B:B,"not found",0) -> Electra Townie Original 7D EQ - Women's - 2016 | I2: =(D2*E2)-F2 -> 599.79
A3: 1 | B3: 2 | C3: 8 | D3: 2 | E3: 1799.99 | F3: 0.07 | G3: =(E3*D3)-F3 -> 3599.91 | H3: =_xlfn.XLOOKUP(C3,Product!A:A,Product!B:B,"not found",0) -> Trek Remedy 29 Carbon Frameset - 2016 | I3: =(D3*E3)-F3 -> 3599.91
A4: 1 | B4: 3 | C4: 10 | D4: 2 | E4: 1549 | F4: 0.05 | G4: =(E4*D4)-F4 -> 3097.95 | H4: =_xlfn.XLOOKUP(C4,Product!A:A,Product!B:B,"not found",0) -> Surly Straggler - 2016 | I4: =(D4*E4)-F4 -> 3097.95
A5: 1 | B5: 4 | C5: 16 | D5: 2 | E5: 599.99 | F5: 0.05 | G5: =(E5*D5)-F5 -> 1199.93 | H5: =_xlfn.XLOOKUP(C5,Product!A:A,Product!B:B,"not found",0) -> Electra Townie Original 7D EQ - 2016 | I5: =(D5*E5)-F5 -> 1199.93
A6: 1 | B6: 5 | C6: 4 | D6: 1 | E6: 2899.99 | F6: 0.2 | G6: =(E6*D6)-F6 -> 2899.79 | H6: =_xlfn.XLOOKUP(C6,Product!A:A,Product!B:B,"not found",0) -> Trek Fuel EX 8 29 - 2016 | I6: =(D6*E6)-F6 -> 2899.79
A7: 2 | B7: 1 | C7: 20 | D7: 1 | E7: 599.99 | F7: 0.07 | G7: =(E7*D7)-F7 -> 599.92 | H7: =_xlfn.XLOOKUP(C7,Product!A:A,Product!B:B,"not found",0) -> Electra Townie Original 7D EQ - Women's - 2016 | I7: =(D7*E7)-F7 -> 599.92
A8: 2 | B8: 2 | C8: 16 | D8: 2 | E8: 599.99 | F8: 0.05 | G8: =(E8*D8)-F8 -> 1199.93 | H8: =_xlfn.XLOOKUP(C8,Product!A:A,Product!B:B,"not found",0) -> Electra Townie Original 7D EQ - 2016 | I8: =(D8*E8)-F8 -> 1199.93
A9: 3 | B9: 1 | C9: 3 | D9: 1 | E9: 999.99 | F9: 0.05 | G9: =(E9*D9)-F9 -> 999.94 | H9: =_xlfn.XLOOKUP(C9,Product!A:A,Product!B:B,"not found",0) -> Surly Wednesday Frameset - 2016 | I9: =(D9*E9)-F9 -> 999.94
A10: 3 | B10: 2 | C10: 20 | D10: 1 | E10: 599.99 | F10: 0.05 | G10: =(E10*D10)-F10 -> 599.94 | H10: =_xlfn.XLOOKUP(C10,Product!A:A,Product!B:B,"not found",0) -> Electra Townie Original 7D EQ - Women's - 2016 | I10: =(D10*E10)-F10 -> 599.94
A11: 4 | B11: 1 | C11: 2 | D11: 2 | E11: 749.99 | F11: 0.1 | G11: =(E11*D11)-F11 -> 1499.88 | H11: =_xlfn.XLOOKUP(C11,Product!A:A,Product!B:B,"not found",0) -> Ritchey Timberwolf Frameset - 2016 | I11: =(D11*E11)-F11 -> 1499.88
A12: 5 | B12: 1 | C12: 10 | D12: 2 | E12: 1549 | F12: 0.05 | G12: =(E12*D12)-F12 -> 3097.95 | H12: =_xlfn.XLOOKUP(C12,Product!A:A,Product!B:B,"not found",0) -> Surly Straggler - 2016 | I12: =(D12*E12)-F12 -> 3097.95
A13: 5 | B13: 2 | C13: 17 | D13: 1 | E13: 429 | F13: 0.07 | G13: =(E13*D13)-F13 -> 428.93 | H13: =_xlfn.XLOOKUP(C13,Product!A:A,Product!B:B,"not found",0) -> Pure Cycles Vine 8-Speed - 2016 | I13: =(D13*E13)-F13 -> 428.93
... A4723: 1615 | B4723: 3 | C4723: 182 | D4723: 1 | E4723: 2499.99 | F4723: 0.2 | G4723: =(E4723*D4723)-F4723 -> 2499.79 | H4723: =_xlfn.XLOOKUP(C4723,Product!A:A,Product!B:B,"not found",0) -> Trek Domane SL 5 Disc - 2018 | I4723: =(D4723*E4723)-F4723 -> 2499.79

Sheet Product
A1: product_id | B1: product_name | C1: brand_id | D1: category_id | E1: model_year | F1: list_price | G1: Product Category | H1: Total sales
A2: 1 | B2: Trek 820 - 2016 | C2: 9 | D2: 6 | E2: 2016 | F2: 379.99 | G2: =_xlfn.XLOOKUP(D2,category!A:A,category!B:B,"not found",0) -> Mountain Bikes | H2: =(order_items!D2*order_items!E2)-order_items!F2 -> 599.79
A3: 2 | B3: Ritchey Timberwolf Frameset - 2016 | C3: 5 | D3: 6 | E3: 2016 | F3: 749.99 | G3: =_xlfn.XLOOKUP(D3,category!A:A,category!B:B,"not found",0) -> Mountain Bikes | H3: =(order_items!D3*order_items!E3)-order_items!F3 -> 3599.91
A4: 3 | B4: Surly Wednesday Frameset - 2016 | C4: 8 | D4: 6 | E4: 2016 | F4: 999.99 | G4: =_xlfn.XLOOKUP(D4,category!A:A,category!B:B,"not found",0) -> Mountain Bikes | H4: =(order_items!D4*order_items!E4)-order_items!F4 -> 3097.95
A5: 4 | B5: Trek Fuel EX 8 29 - 2016 | C5: 9 | D5: 6 | E5: 2016 | F5: 2899.99 | G5: =_xlfn.XLOOKUP(D5,category!A:A,category!B:B,"not found",0) -> Mountain Bikes | H5: =(order_items!D5*order_items!E5)-order_items!F5 -> 1199.93
A6: 5 | B6: Heller Shagamaw Frame - 2016 | C6: 3 | D6: 6 | E6: 2016 | F6: 1320.99 | G6: =_xlfn.XLOOKUP(D6,category!A:A,category!B:B,"not found",0) -> Mountain Bikes | H6: =(order_items!D6*order_items!E6)-order_items!F6 -> 2899.79
A7: 6 | B7: Surly Ice Cream Truck Frameset - 2016 | C7: 8 | D7: 6 | E7: 2016 | F7: 469.99 | G7: =_xlfn.XLOOKUP(D7,category!A:A,category!B:B,"not found",0) -> Mountain Bikes | H7: =(order_items!D7*order_items!E7)-order_items!F7 -> 599.92
A8: 7 | B8: Trek Slash 8 27.5 - 2016 | C8: 9 | D8: 6 | E8: 2016 | F8: 3999.99 | G8: =_xlfn.XLOOKUP(D8,category!A:A,category!B:B,"not found",0) -> Mountain Bikes | H8: =(order_items!D8*order_items!E8)-order_items!F8 -> 1199.93
A9: 8 | B9: Trek Remedy 29 Carbon Frameset - 2016 | C9: 9 | D9: 6 | E9: 2016 | F9: 1799.99 | G9: =_xlfn.XLOOKUP(D9,category!A:A,category!B:B,"not found",0) -> Mountain Bikes | H9: =(order_items!D9*order_items!E9)-order_items!F9 -> 999.94
A10: 9 | B10: Trek Conduit+ - 2016 | C10: 9 | D10: 5 | E10: 2016 | F10: 2999.99 | G10: =_xlfn.XLOOKUP(D10,category!A:A,category!B:B,"not found",0) -> Electric Bikes | H10: =(order_items!D10*order_items!E10)-order_items!F10 -> 599.94
A11: 10 | B11: Surly Straggler - 2016 | C11: 8 | D11: 4 | E11: 2016 | F11: 1549 | G11: =_xlfn.XLOOKUP(D11,category!A:A,category!B:B,"not found",0) -> Cyclocross Bicycles | H11: =(order_items!D11*order_items!E11)-order_items!F11 -> 1499.88
A12: 11 | B12: Surly Straggler 650b - 2016 | C12: 8 | D12: 4 | E12: 2016 | F12: 1680.99 | G12: =_xlfn.XLOOKUP(D12,category!A:A,category!B:B,"not found",0) -> Cyclocross Bicycles | H12: =(order_items!D12*order_items!E12)-order_items!F12 -> 3097.95
A13: 12 | B13: Electra Townie Original 21D - 2016 | C13: 1 | D13: 3 | E13: 2016 | F13: 549.99 | G13: =_xlfn.XLOOKUP(D13,category!A:A,category!B:B,"not found",0) -> Cruisers Bicycles | H13: =(order_items!D13*order_items!E13)-order_items!F13 -> 428.93
... A322: 321 | B322: Trek Checkpoint ALR Frameset - 2019 | C322: 9 | D322: 7 | E322: 2019 | F322: 3199.99 | G322: =_xlfn.XLOOKUP(D322,category!A:A,category!B:B,"not found",0) -> Road Bikes | H322: =(order_items!D322*order_items!E322)-order_items!F322 -> 539.88

Sheet category
A1: category_id | B1: category_name
A2: 1 | B2: Children Bicycles
A3: 2 | B3: Comfort Bicycles
A4: 3 | B4: Cruisers Bicycles
A5: 4 | B5: Cyclocross Bicycles
A6: 5 | B6: Electric Bikes
A7: 6 | B7: Mountain Bikes
A8: 7 | B8: Road Bikes

Sheet Pivot table
A1: Row Labels | B1: Sum of Total sales
A2: Children Bicycles | B2: 96886.83
A3: Comfort Bicycles | B3: 47090.56
A4: Cruisers Bicycles | B4: 118050.4
A5: Cyclocross Bicycles | B5: 14214
A6: Electric Bikes | B6: 20005.78
A7: Mountain Bikes | B7: 87895.84
A8: Road Bikes | B8: 73152.91
A9: Grand Total | B9: 457296.32
